[
  {
    "__type__": "cc.SpriteFrame",
    "content": {
      "name": "ae_target03",
      "texture": "0cKovDEIFDULS+4cz/z24q",
      "rect": [
        43,
        64,
        183,
        193
      ],
      "offset": [
        -16.5,
        -9.5
      ],
      "originalSize": [
        302,
        302
      ],
      "capInsets": [
        0,
        0,
        0,
        0
      ]
    }
  },
  {
    "__type__": "cc.SpriteFrame",
    "content": {
      "name": "ae_target10",
      "texture": "49O5PQVzNHspWk44RMndLz",
      "rect": [
        66,
        77,
        166,
        166
      ],
      "offset": [
        -2,
        -9
      ],
      "originalSize": [
        302,
        302
      ],
      "capInsets": [
        0,
        0,
        0,
        0
      ]
    }
  },
  {
    "__type__": "cc.SpriteFrame",
    "content": {
      "name": "ae_target06",
      "texture": "3eIfhPMO9OkZsnD3ms1KNL",
      "rect": [
        51,
        83,
        193,
        185
      ],
      "offset": [
        -3.5,
        -24.5
      ],
      "originalSize": [
        302,
        302
      ],
      "capInsets": [
        0,
        0,
        0,
        0
      ]
    }
  },
  {
    "__type__": "cc.SpriteFrame",
    "content": {
      "name": "ae_target05",
      "texture": "99SIgzyjJI1I+VAr3TXlix",
      "rect": [
        53,
        78,
        171,
        176
      ],
      "offset": [
        -12.5,
        -15
      ],
      "originalSize": [
        302,
        302
      ],
      "capInsets": [
        0,
        0,
        0,
        0
      ]
    }
  },
  {
    "__type__": "cc.SpriteFrame",
    "content": {
      "name": "ae_target02",
      "texture": "f1OpTpKehM7rWgXC8cm16o",
      "rect": [
        37,
        54,
        196,
        203
      ],
      "offset": [
        -16,
        -4.5
      ],
      "originalSize": [
        302,
        302
      ],
      "capInsets": [
        0,
        0,
        0,
        0
      ]
    }
  },
  {
    "__type__": "cc.SpriteFrame",
    "content": {
      "name": "ae_target04",
      "texture": "66sTRdCf9KJL32cIq/YMr9",
      "rect": [
        45,
        68,
        179,
        189
      ],
      "offset": [
        -16.5,
        -11.5
      ],
      "originalSize": [
        302,
        302
      ],
      "capInsets": [
        0,
        0,
        0,
        0
      ]
    }
  },
  {
    "__type__": "cc.SpriteFrame",
    "content": {
      "name": "ae_target08",
      "texture": "c89Cdg2oBES5TKyq7hvdAk",
      "rect": [
        75,
        87,
        148,
        148
      ],
      "offset": [
        -2,
        -10
      ],
      "originalSize": [
        302,
        302
      ],
      "capInsets": [
        0,
        0,
        0,
        0
      ]
    }
  },
  {
    "__type__": "cc.SpriteFrame",
    "content": {
      "name": "ae_target07",
      "texture": "37j3Gf8T5HkrMe1hJwJCAf",
      "rect": [
        49,
        76,
        208,
        199
      ],
      "offset": [
        2,
        -24.5
      ],
      "originalSize": [
        302,
        302
      ],
      "capInsets": [
        0,
        0,
        0,
        0
      ]
    }
  },
  {
    "__type__": "cc.SpriteFrame",
    "content": {
      "name": "ae_target09",
      "texture": "f8JN6EwHdJoojUFB2h2upz",
      "rect": [
        68,
        79,
        162,
        162
      ],
      "offset": [
        -2,
        -9
      ],
      "originalSize": [
        302,
        302
      ],
      "capInsets": [
        0,
        0,
        0,
        0
      ]
    }
  },
  {
    "__type__": "cc.AnimationClip",
    "_name": "target",
    "_duration": 1.5166666666666666,
    "wrapMode": "2",
    "curveData": {
      "comps": {
        "cc.Sprite": {
          "spriteFrame": [
            {
              "frame": 0,
              "value": {
                "__uuid__": "d4kymu3VhLgK+CIzIRj4Hz"
              }
            },
            {
              "frame": 0.16666666666666666,
              "value": {
                "__uuid__": "59keLSlL1DD6Gw5porMgqH"
              }
            },
            {
              "frame": 0.3333333333333333,
              "value": {
                "__uuid__": "13IzAb2FJCgqI1iaHpvc0b"
              }
            },
            {
              "frame": 0.5,
              "value": {
                "__uuid__": "5bgAgosl1JQKJHIjBTbm85"
              }
            },
            {
              "frame": 0.6666666666666666,
              "value": {
                "__uuid__": "4fsIh33x9DjqOabXu1gaF+"
              }
            },
            {
              "frame": 0.8333333333333334,
              "value": {
                "__uuid__": "33fufl/XdLZ6p9agga1PXN"
              }
            },
            {
              "frame": 1,
              "value": {
                "__uuid__": "82TY4vR4NACKzd7lfJzLPt"
              }
            },
            {
              "frame": 1.1666666666666667,
              "value": {
                "__uuid__": "6f0qnUJp1LS6qOUHlKrayI"
              }
            },
            {
              "frame": 1.3333333333333333,
              "value": {
                "__uuid__": "91GYIExrdHDrHA5m7L7ZHp"
              }
            },
            {
              "frame": 1.5,
              "value": {
                "__uuid__": "2btq0m/bZJR619K7nJIEtK"
              }
            }
          ]
        }
      }
    }
  },
  {
    "__type__": "cc.SpriteFrame",
    "content": {
      "name": "ae_target01",
      "texture": "70NXgl3OFBO6U6oLeY1Hyq",
      "rect": [
        33,
        46,
        205,
        213
      ],
      "offset": [
        -15.5,
        -1.5
      ],
      "originalSize": [
        302,
        302
      ],
      "capInsets": [
        0,
        0,
        0,
        0
      ]
    }
  }
]